xga_agent_tool/__init__.py
xga_agent_tool/a2a_tool_proxy_app.py
xga_agent_tool/tool_base.py
xga_agent_tool/a2a/base.py
xga_agent_tool/a2a/config.py
xga_agent_tool/a2a/helper.py
xga_agent_tool/utils/setup_env.py
xga_agent_tool-0.1.1.dist-info/METADATA
xga_agent_tool-0.1.1.dist-info/WHEEL
xga_agent_tool-0.1.1.dist-info/entry_points.txt
xga_agent_tool-0.1.1.dist-info/RECORD
